[
  {"metric":{"path":"/tool/atom-beautify"},"value":[1648851625.911,"6"]},
  {"metric":{"path":"/tool/bandit"},"value":[1648851625.911,"7"]},
  {"metric":{"path":"/tool/better-code-hub"},"value":[1648851625.911,"9"]},
  {"metric":{"path":"/tool/binskim"},"value":[1648851625.911,"6"]},
  {"metric":{"path":"/tool/callgraph"},"value":[1648851625.911,"11"]},
  {"metric":{"path":"/tool/classgraph"},"value":[1648851625.911,"7"]},
  {"metric":{"path":"/tool/codescene"},"value":[1648851625.911,"24"]},
  {"metric":{"path":"/tool/coverity"},"value":[1648851625.911,"9"]},
  {"metric":{"path":"/tool/eslint"},"value":[1648851625.911,"12"]},
  {"metric":{"path":"/tool/fortify"},"value":[1648851625.911,"7"]},
  {"metric":{"path":"/tool/golangci-lint"},"value":[1648851625.911,"9"]},
  {"metric":{"path":"/tool/lizard"},"value":[1648851625.911,"8"]},
  {"metric":{"path":"/tool/manalyze"},"value":[1648851625.911,"6"]},
  {"metric":{"path":"/tool/mega-linter"},"value":[1648851625.911,"37"]},
  {"metric":{"path":"/tool/phpstan"},"value":[1648851625.911,"8"]},
  {"metric":{"path":"/tool/semgrep"},"value":[1648851625.911,"11"]},
  {"metric":{"path":"/tool/shiftleft"},"value":[1648851625.911,"7"]},
  {"metric":{"path":"/tool/shiftleft-scan"},"value":[1648851625.911,"8"]},
  {"metric":{"path":"/tool/sonarqube"},"value":[1648851625.911,"11"]},
  {"metric":{"path":"/tool/sonatype"},"value":[1648851625.911,"29"]},
  {"metric":{"path":"/tool/teamscale"},"value":[1648851625.911,"6"]},
  {"metric":{"path":"/tool/trivy"},"value":[1648851625.911,"7"]},
  {"metric":{"path":"/tool/understand"},"value":[1648851625.911,"11"]},
  {"metric":{"path":"/tool/unibeautify"},"value":[1648851625.911,"8"]},
  {"metric":{"path":"/tool/zpa"},"value":[1648851625.911,"7"]}
]