[
  {"metric":{"path":"/tool/better-code-hub"},"value":[1672265810.967,"7"]},
  {"metric":{"path":"/tool/black"},"value":[1672265810.967,"10"]},
  {"metric":{"path":"/tool/callgraph"},"value":[1672265810.967,"11"]},
  {"metric":{"path":"/tool/cargo-audit"},"value":[1672265810.967,"8"]},
  {"metric":{"path":"/tool/cargo-expand"},"value":[1672265810.967,"8"]},
  {"metric":{"path":"/tool/clayton"},"value":[1672265810.967,"7"]},
  {"metric":{"path":"/tool/cmetrics"},"value":[1672265810.967,"8"]},
  {"metric":{"path":"/tool/codeql"},"value":[1672265810.967,"9"]},
  {"metric":{"path":"/tool/codescene"},"value":[1672265810.967,"17"]},
  {"metric":{"path":"/tool/coverity"},"value":[1672265810.967,"11"]},
  {"metric":{"path":"/tool/cwe_checker"},"value":[1672265810.967,"8"]},
  {"metric":{"path":"/tool/deepsource"},"value":[1672265810.967,"9"]},
  {"metric":{"path":"/tool/diktat"},"value":[1672265810.967,"8"]},
  {"metric":{"path":"/tool/embold"},"value":[1672265810.967,"7"]},
  {"metric":{"path":"/tool/fortify"},"value":[1672265810.967,"7"]},
  {"metric":{"path":"/tool/lizard"},"value":[1672265810.967,"8"]},
  {"metric":{"path":"/tool/mega-linter"},"value":[1672265810.967,"30"]},
  {"metric":{"path":"/tool/mypy"},"value":[1672265810.967,"11"]},
  {"metric":{"path":"/tool/njsscan"},"value":[1672265810.967,"11"]},
  {"metric":{"path":"/tool/nodejsscan"},"value":[1672265810.967,"7"]},
  {"metric":{"path":"/tool/polyspace-code-prover"},"value":[1672265810.967,"7"]},
  {"metric":{"path":"/tool/semgrep"},"value":[1672265810.967,"21"]},
  {"metric":{"path":"/tool/sonatype"},"value":[1672265810.967,"7"]},
  {"metric":{"path":"/tool/teamscale"},"value":[1672265810.967,"13"]},
  {"metric":{"path":"/tool/whitehat-application-security-platform"},"value":[1672265810.967,"8"]}
]