[
  {"metric":{"path":"/tool/atom-beautify"},"value":[1654554116.397,"8"]},
  {"metric":{"path":"/tool/aws-cloudformation-guard"},"value":[1654554116.397,"6"]},
  {"metric":{"path":"/tool/bodyclose"},"value":[1654554116.397,"6"]},
  {"metric":{"path":"/tool/code-cracker"},"value":[1654554116.397,"8"]},
  {"metric":{"path":"/tool/codescene"},"value":[1654554116.397,"9"]},
  {"metric":{"path":"/tool/coverity"},"value":[1654554116.397,"6"]},
  {"metric":{"path":"/tool/cqmetrics"},"value":[1654554116.397,"6"]},
  {"metric":{"path":"/tool/deepcode"},"value":[1654554116.397,"6"]},
  {"metric":{"path":"/tool/fix-insight"},"value":[1654554116.397,"7"]},
  {"metric":{"path":"/tool/jeb-decompiler"},"value":[1654554116.397,"10"]},
  {"metric":{"path":"/tool/lizard"},"value":[1654554116.397,"6"]},
  {"metric":{"path":"/tool/mccabe"},"value":[1654554116.397,"8"]},
  {"metric":{"path":"/tool/mega-linter"},"value":[1654554116.397,"25"]},
  {"metric":{"path":"/tool/phasar"},"value":[1654554116.397,"6"]},
  {"metric":{"path":"/tool/polyspace-code-prover"},"value":[1654554116.397,"6"]},
  {"metric":{"path":"/tool/prusti"},"value":[1654554116.397,"6"]},
  {"metric":{"path":"/tool/pycodequal"},"value":[1654554116.397,"9"]},
  {"metric":{"path":"/tool/pylint"},"value":[1654554116.397,"7"]},
  {"metric":{"path":"/tool/reviewdog"},"value":[1654554116.397,"7"]},
  {"metric":{"path":"/tool/rubrowser"},"value":[1654554116.397,"6"]},
  {"metric":{"path":"/tool/semgrep"},"value":[1654554116.397,"12"]},
  {"metric":{"path":"/tool/sonarqube"},"value":[1654554116.397,"9"]},
  {"metric":{"path":"/tool/sqlcheck"},"value":[1654554116.397,"7"]},
  {"metric":{"path":"/tool/todocheck"},"value":[1654554116.397,"7"]},
  {"metric":{"path":"/tool/understand"},"value":[1654554116.397,"10"]}
]