{
  "applicationinspector": "5",
  "atom-beautify": "6",
  "better-code-hub": "6",
  "black": "9",
  "ckjm": "5",
  "codacy": "5",
  "codescene": "7",
  "coverity": "8",
  "eslint": "9",
  "go-vet": "5",
  "mega-linter": "30",
  "mypy": "7",
  "phpstan": "8",
  "pre-commit": "15",
  "rudra": "6",
  "semgrep": "13",
  "sonatype": "10",
  "spoon": "8",
  "sqlcheck": "7",
  "teamscale": "5",
  "tencentcodeanalysis": "5",
  "tscancode": "6",
  "tsqlrules": "6",
  "understand": "10",
  "unibeautify": "5"
}
